scltnn/__init__.py
scltnn/_pseudotimekernel.py
scltnn/datasets.py
scltnn/models.py
scltnn/plot.py
scltnn-0.1.0.dist-info/LICENSE
scltnn-0.1.0.dist-info/METADATA
scltnn-0.1.0.dist-info/WHEEL
scltnn-0.1.0.dist-info/top_level.txt
scltnn-0.1.0.dist-info/RECORD
