Metadata-Version: 2.1
Name: scltnn
Version: 0.1.0
Summary: A library to calculate the latent time of scRNA-seq
Home-page: https://github.com/Starlitnightly/scltnn
Author: starlitnightly
Author-email: starlitnightly@163.com
Classifier: Programming Language :: Python :: 3
Classifier: Operating System :: OS Independent
Requires-Python: >=3.8
License-File: LICENSE
Requires-Dist: scanpy >=1.9
Requires-Dist: numpy >=1.22
Requires-Dist: pandas >=1.4
Requires-Dist: distfit
